whitegravel/__init__.py
whitegravel/app/__init__.py
whitegravel/app/app.py
whitegravel/app/classes/__init__.py
whitegravel/app/classes/base.py
whitegravel/app/classes/token.py
whitegravel/app/classes/user.py
whitegravel/app/controllers/__init__.py
whitegravel/app/controllers/base.py
whitegravel/app/controllers/token.py
whitegravel/app/controllers/user.py
whitegravel/app/exceptions/__init__.py
whitegravel/app/exceptions/base.py
whitegravel/app/exceptions/controllers.py
whitegravel/app/forms/__init__.py
whitegravel/app/forms/base.py
whitegravel/app/forms/create_user_form.py
whitegravel/app/forms/mfa_login_form.py
whitegravel/app/routes/__init__.py
whitegravel/app/routes/auth.py
whitegravel/app/routes/users.py
whitegravel/app/security/auth.py
whitegravel/app/security/mfa.py
whitegravel/app/security/passwords.py
whitegravel/cli/__init__.py
whitegravel/cli/functions.py
whitegravel/cli/app/__init__.py
whitegravel/cli/app/setup.py
whitegravel/cli/app/start.py
whitegravel/cli/db/__init__.py
whitegravel/cli/db/app.py
whitegravel/config/__init__.py
whitegravel/config/loader.py
whitegravel/config/model.py
whitegravel/constants/__init__.py
whitegravel/constants/app.py
whitegravel/constants/metadata.py
whitegravel/db/__init__.py
whitegravel/db/alembic/__init__.py
whitegravel/db/alembic/alembic.py
whitegravel/db/alembic/app/__init__.py
whitegravel/db/alembic/app/env.py
whitegravel/db/alembic/app/script.py.mako
whitegravel/db/alembic/app/versions/2023_07_26_1411-0ac49eec333a_init.py
whitegravel/db/alembic/app/versions/2023_07_26_2005-ac6d38c47cdf_new_table_token.py
whitegravel/db/alembic/app/versions/2023_07_27_1619-df896b3ce300_token_created_at_and_token_expiration.py
whitegravel/db/app/__init__.py
whitegravel/db/app/base.py
whitegravel/db/app/functions.py
whitegravel/db/app/querysets/__init__.py
whitegravel/db/app/tables/__init__.py
whitegravel/db/app/tables/token.py
whitegravel/db/app/tables/user.py
whitegravel/exceptions/__init__.py
whitegravel/exceptions/base.py
whitegravel-0.1.0a1.dist-info/LICENSE
whitegravel-0.1.0a1.dist-info/METADATA
whitegravel-0.1.0a1.dist-info/WHEEL
whitegravel-0.1.0a1.dist-info/entry_points.txt
whitegravel-0.1.0a1.dist-info/top_level.txt
whitegravel-0.1.0a1.dist-info/RECORD
