Metadata-Version: 2.1
Name: whitegravel
Version: 0.1.0a1
Summary: All-in-one Cybersecurity Management Platform
Author-email: Juan Cerezo <jcerezo.dev@proton.me>
License: GPL-3.0-only
Classifier: Programming Language :: Python :: 3
Requires-Python: >=3.11
License-File: LICENSE
Requires-Dist: dynaconf (<3.2.0,>=3.1.12)
Requires-Dist: click (<8.2.0,>=8.1.3)
Requires-Dist: fastapi (<0.97.0,>=0.96.1)
Requires-Dist: uvicorn (<0.23.0,>=0.22.0)
Requires-Dist: pydantic (<1.11.0,>=1.10.9)
Requires-Dist: sqlalchemy (<2.1.0,>=2.0.15)
Requires-Dist: email-validator (<2.1.0,>=2.0.0)
Requires-Dist: dnspython (<2.4.0,>=2.3.0)
Requires-Dist: passlib[bcrypt] (<1.8.0,>=1.7.4)
Requires-Dist: python-jose[cryptography] (<3.4.0,>=3.3.0)
Requires-Dist: python-multipart (<0.1.0,>=0.0.6)
Requires-Dist: pyotp (<2.9.0,>=2.8.0)
Requires-Dist: alembic (<1.12.0,>=1.11.1)
Requires-Dist: psycopg2 (<2.10.0,>=2.9.6)
Requires-Dist: qrcode (<7.5.0,>=7.4.2)
